{
  "rsus": [
    {
      "rsu_id": 1,
      "sk_hex": "ec0b63fbded3262cbc84113d2867a463911bbd44d19913814118f4734e975721",
      "pk_hex": "5078b998e4f02a459dd3af140072daeb9a8226be0594bd9f0f5a59d0fa7fd256"
    },
    {
      "rsu_id": 2,
      "sk_hex": "6fac3e0f2c4389b498bb1a1cfaae693a74e6fc0695d03c09e0f9d232a2615546",
      "pk_hex": "9743fd83c8b825780fba5a3404fc9536cc306dc1eabb46a61bcb005fa04f73e3"
    },
    {
      "rsu_id": 3,
      "sk_hex": "c2d090c2e270471c335ca61d990f42ba75a67965e321e35c620b172e630e7466",
      "pk_hex": "3eda2f757bb8a8c6f3ca5738edb8c9965641c27845e17b8a0804bd47e59c5231"
    },
    {
      "rsu_id": 4,
      "sk_hex": "d3414902596d31ad989000e23a99843bd9688554576d76976ce2726ff86fb505",
      "pk_hex": "41ce1de24e3e449ff567d16f13472260df6537a9696f470a458871674ace77c0"
    }
  ],
  "events": [
    {
      "token": {
        "version": 1,
        "region_id": "NET",
        "window_id": 1,
        "nonce": 18093939240302112128,
        "expiry_ts": 1764404472,
        "rsu_id": 1,
        "signature_hex": "bd5f0b884b4090e1bd54da8cd3e0a8096fc985fac057e7fac5f6f8f1b8f891c9"
      },
      "lat": 31.200499999999998,
      "lon": 121.40100000000001,
      "geohash7": "wtw3s90",
      "timestamp": 1764400812
    },
    {
      "token": {
        "version": 1,
        "region_id": "NET",
        "window_id": 1,
        "nonce": 17860587875065357597,
        "expiry_ts": 1764404472,
        "rsu_id": 2,
        "signature_hex": "c4753858a35e420ab8b1b2d322dbbee05d7ff52ba4737b882fbaded05c71fe7a"
      },
      "lat": 31.201,
      "lon": 121.402,
      "geohash7": "wtw3s90",
      "timestamp": 1764400812
    },
    {
      "token": {
        "version": 1,
        "region_id": "NET",
        "window_id": 1,
        "nonce": 11347897929025816933,
        "expiry_ts": 1764404472,
        "rsu_id": 3,
        "signature_hex": "26c2ed96b84cfbb25bfd5cbcf53e533f78169827ad16417e6439e5297c21746a"
      },
      "lat": 31.2015,
      "lon": 121.403,
      "geohash7": "wtw3s90",
      "timestamp": 1764400812
    },
    {
      "token": {
        "version": 1,
        "region_id": "NET",
        "window_id": 1,
        "nonce": 11110882564426344320,
        "expiry_ts": 1764404472,
        "rsu_id": 4,
        "signature_hex": "cbadffbcde94f04d94ce43945486c7379ad7711bdd4d121508ce68d4ffefd61c"
      },
      "lat": 31.201999999999998,
      "lon": 121.40400000000001,
      "geohash7": "wtw3s90",
      "timestamp": 1764400812
    },
    {
      "token": {
        "version": 1,
        "region_id": "NET",
        "window_id": 2,
        "nonce": 5157855664095185713,
        "expiry_ts": 1764404532,
        "rsu_id": 1,
        "signature_hex": "a15c73b38dc37879d26e343b2114fb586be9d502e9566ef1c906f7165d4f96f9"
      },
      "lat": 31.200499999999998,
      "lon": 121.40100000000001,
      "geohash7": "wtw3s90",
      "timestamp": 1764400872
    },
    {
      "token": {
        "version": 1,
        "region_id": "NET",
        "window_id": 2,
        "nonce": 17716037147302256420,
        "expiry_ts": 1764404532,
        "rsu_id": 2,
        "signature_hex": "5651d351154f3ce9d7ba2e1994ee81193b578202b0dc464ae50951645d00b601"
      },
      "lat": 31.201,
      "lon": 121.402,
      "geohash7": "wtw3s90",
      "timestamp": 1764400872
    },
    {
      "token": {
        "version": 1,
        "region_id": "NET",
        "window_id": 2,
        "nonce": 18073394148435068360,
        "expiry_ts": 1764404532,
        "rsu_id": 3,
        "signature_hex": "b9949bd44644f0ddb99f36c33f524e72321acdf7e920e3f3d398dbef46eb5efd"
      },
      "lat": 31.2015,
      "lon": 121.403,
      "geohash7": "wtw3s90",
      "timestamp": 1764400872
    },
    {
      "token": {
        "version": 1,
        "region_id": "NET",
        "window_id": 2,
        "nonce": 15895038034724545895,
        "expiry_ts": 1764404532,
        "rsu_id": 4,
        "signature_hex": "155be4e4df4cd3da1b8b511de2efbee59b187073e22bd7eff50b0b1deed81650"
      },
      "lat": 31.201999999999998,
      "lon": 121.40400000000001,
      "geohash7": "wtw3s90",
      "timestamp": 1764400872
    },
    {
      "token": {
        "version": 1,
        "region_id": "NET",
        "window_id": 3,
        "nonce": 17990441267317969852,
        "expiry_ts": 1764404592,
        "rsu_id": 1,
        "signature_hex": "97edd720ac02ded2d4a0e6bad6f184b5cafeda74ee14731a729c211c8b321e00"
      },
      "lat": 31.200499999999998,
      "lon": 121.40100000000001,
      "geohash7": "wtw3s90",
      "timestamp": 1764400932
    },
    {
      "token": {
        "version": 1,
        "region_id": "NET",
        "window_id": 3,
        "nonce": 1737731027228228108,
        "expiry_ts": 1764404592,
        "rsu_id": 2,
        "signature_hex": "48fd8c9116ef870441029cf0c7655f434231cbc3ff6883f3e0c8dc26705950e5"
      },
      "lat": 31.201,
      "lon": 121.402,
      "geohash7": "wtw3s90",
      "timestamp": 1764400932
    },
    {
      "token": {
        "version": 1,
        "region_id": "NET",
        "window_id": 3,
        "nonce": 18060464491598699,
        "expiry_ts": 1764404592,
        "rsu_id": 3,
        "signature_hex": "322b95aea5a4ee47d2da56c95e18c38a2729404bdfb71a0bacae2b239c39823a"
      },
      "lat": 31.2015,
      "lon": 121.403,
      "geohash7": "wtw3s90",
      "timestamp": 1764400932
    },
    {
      "token": {
        "version": 1,
        "region_id": "NET",
        "window_id": 3,
        "nonce": 10109310992021956893,
        "expiry_ts": 1764404592,
        "rsu_id": 4,
        "signature_hex": "a0f4394eb2aac992e1840e13de807ab6d2ed1485ca90c7f160755f1f8a134d2f"
      },
      "lat": 31.201999999999998,
      "lon": 121.40400000000001,
      "geohash7": "wtw3s90",
      "timestamp": 1764400932
    },
    {
      "token": {
        "version": 1,
        "region_id": "NET",
        "window_id": 4,
        "nonce": 16723227743168305085,
        "expiry_ts": 1764404652,
        "rsu_id": 1,
        "signature_hex": "43a65acadb242e418c6c07e69a4232eb6aec1112af171a34a5927871394f2daf"
      },
      "lat": 31.200499999999998,
      "lon": 121.40100000000001,
      "geohash7": "wtw3s90",
      "timestamp": 1764400992
    },
    {
      "token": {
        "version": 1,
        "region_id": "NET",
        "window_id": 4,
        "nonce": 3836696649066808506,
        "expiry_ts": 1764404652,
        "rsu_id": 2,
        "signature_hex": "8ba3ebdd2761a21dd44150662237877866d9ac7e166ca5645243b5e6ec264efc"
      },
      "lat": 31.201,
      "lon": 121.402,
      "geohash7": "wtw3s90",
      "timestamp": 1764400992
    },
    {
      "token": {
        "version": 1,
        "region_id": "NET",
        "window_id": 4,
        "nonce": 2098157794777802872,
        "expiry_ts": 1764404652,
        "rsu_id": 3,
        "signature_hex": "ddf94393dbfb17c6097deb9ea1c5cded63f352f2d6f3a67f9a5aa2ca36ebe0fe"
      },
      "lat": 31.2015,
      "lon": 121.403,
      "geohash7": "wtw3s90",
      "timestamp": 1764400992
    },
    {
      "token": {
        "version": 1,
        "region_id": "NET",
        "window_id": 4,
        "nonce": 9453017485210572692,
        "expiry_ts": 1764404652,
        "rsu_id": 4,
        "signature_hex": "46122f3e0639e9e6c0f52fe826ee2a82876450aecf8598f2111292d56b8f8a27"
      },
      "lat": 31.201999999999998,
      "lon": 121.40400000000001,
      "geohash7": "wtw3s90",
      "timestamp": 1764400992
    },
    {
      "token": {
        "version": 1,
        "region_id": "NET",
        "window_id": 5,
        "nonce": 14303045954748402419,
        "expiry_ts": 1764404712,
        "rsu_id": 1,
        "signature_hex": "53ebfdadcd698b18239d027b55aa1a7301a56ee13859ee1e228aa634f6763de1"
      },
      "lat": 31.200499999999998,
      "lon": 121.40100000000001,
      "geohash7": "wtw3s90",
      "timestamp": 1764401052
    },
    {
      "token": {
        "version": 1,
        "region_id": "NET",
        "window_id": 5,
        "nonce": 3306446756078197666,
        "expiry_ts": 1764404712,
        "rsu_id": 2,
        "signature_hex": "685ed95c7906078b208ffd81c40db1bfd16c5bb82e5968230645af034491f2e4"
      },
      "lat": 31.201,
      "lon": 121.402,
      "geohash7": "wtw3s90",
      "timestamp": 1764401052
    },
    {
      "token": {
        "version": 1,
        "region_id": "NET",
        "window_id": 5,
        "nonce": 807227019364386752,
        "expiry_ts": 1764404712,
        "rsu_id": 3,
        "signature_hex": "c102c78b00dd4a5ebfba6f917d6fd31efb1d17e19cf2d7f67a0efac23dd8a980"
      },
      "lat": 31.2015,
      "lon": 121.403,
      "geohash7": "wtw3s90",
      "timestamp": 1764401052
    },
    {
      "token": {
        "version": 1,
        "region_id": "NET",
        "window_id": 5,
        "nonce": 7925384687073543262,
        "expiry_ts": 1764404712,
        "rsu_id": 4,
        "signature_hex": "7a616658f37ac071736e2520442bc07451736f5d4cba0c1187cb9359dd07ada6"
      },
      "lat": 31.201999999999998,
      "lon": 121.40400000000001,
      "geohash7": "wtw3s90",
      "timestamp": 1764401052
    }
  ],
  "metrics": [
    {
      "timestamp": 1.0,
      "vehicle_count": 0,
      "vehicles": []
    },
    {
      "timestamp": 2.0,
      "vehicle_count": 0,
      "vehicles": []
    },
    {
      "timestamp": 3.0,
      "vehicle_count": 0,
      "vehicles": []
    },
    {
      "timestamp": 4.0,
      "vehicle_count": 0,
      "vehicles": []
    },
    {
      "timestamp": 5.0,
      "vehicle_count": 0,
      "vehicles": []
    },
    {
      "timestamp": 6.0,
      "vehicle_count": 0,
      "vehicles": []
    },
    {
      "timestamp": 7.0,
      "vehicle_count": 0,
      "vehicles": []
    },
    {
      "timestamp": 8.0,
      "vehicle_count": 0,
      "vehicles": []
    },
    {
      "timestamp": 9.0,
      "vehicle_count": 0,
      "vehicles": []
    },
    {
      "timestamp": 10.0,
      "vehicle_count": 0,
      "vehicles": []
    },
    {
      "timestamp": 11.0,
      "vehicle_count": 0,
      "vehicles": []
    },
    {
      "timestamp": 12.0,
      "vehicle_count": 0,
      "vehicles": []
    },
    {
      "timestamp": 13.0,
      "vehicle_count": 0,
      "vehicles": []
    },
    {
      "timestamp": 14.0,
      "vehicle_count": 0,
      "vehicles": []
    },
    {
      "timestamp": 15.0,
      "vehicle_count": 0,
      "vehicles": []
    },
    {
      "timestamp": 16.0,
      "vehicle_count": 0,
      "vehicles": []
    },
    {
      "timestamp": 17.0,
      "vehicle_count": 0,
      "vehicles": []
    },
    {
      "timestamp": 18.0,
      "vehicle_count": 0,
      "vehicles": []
    },
    {
      "timestamp": 19.0,
      "vehicle_count": 0,
      "vehicles": []
    },
    {
      "timestamp": 20.0,
      "vehicle_count": 0,
      "vehicles": []
    },
    {
      "timestamp": 21.0,
      "vehicle_count": 0,
      "vehicles": []
    },
    {
      "timestamp": 22.0,
      "vehicle_count": 0,
      "vehicles": []
    },
    {
      "timestamp": 23.0,
      "vehicle_count": 0,
      "vehicles": []
    },
    {
      "timestamp": 24.0,
      "vehicle_count": 0,
      "vehicles": []
    },
    {
      "timestamp": 25.0,
      "vehicle_count": 0,
      "vehicles": []
    },
    {
      "timestamp": 26.0,
      "vehicle_count": 0,
      "vehicles": []
    },
    {
      "timestamp": 27.0,
      "vehicle_count": 0,
      "vehicles": []
    },
    {
      "timestamp": 28.0,
      "vehicle_count": 0,
      "vehicles": []
    },
    {
      "timestamp": 29.0,
      "vehicle_count": 0,
      "vehicles": []
    },
    {
      "timestamp": 30.0,
      "vehicle_count": 0,
      "vehicles": []
    },
    {
      "timestamp": 31.0,
      "vehicle_count": 0,
      "vehicles": []
    },
    {
      "timestamp": 32.0,
      "vehicle_count": 0,
      "vehicles": []
    },
    {
      "timestamp": 33.0,
      "vehicle_count": 0,
      "vehicles": []
    },
    {
      "timestamp": 34.0,
      "vehicle_count": 0,
      "vehicles": []
    },
    {
      "timestamp": 35.0,
      "vehicle_count": 0,
      "vehicles": []
    },
    {
      "timestamp": 36.0,
      "vehicle_count": 0,
      "vehicles": []
    },
    {
      "timestamp": 37.0,
      "vehicle_count": 0,
      "vehicles": []
    },
    {
      "timestamp": 38.0,
      "vehicle_count": 0,
      "vehicles": []
    },
    {
      "timestamp": 39.0,
      "vehicle_count": 0,
      "vehicles": []
    },
    {
      "timestamp": 40.0,
      "vehicle_count": 0,
      "vehicles": []
    },
    {
      "timestamp": 41.0,
      "vehicle_count": 0,
      "vehicles": []
    },
    {
      "timestamp": 42.0,
      "vehicle_count": 0,
      "vehicles": []
    },
    {
      "timestamp": 43.0,
      "vehicle_count": 0,
      "vehicles": []
    },
    {
      "timestamp": 44.0,
      "vehicle_count": 0,
      "vehicles": []
    },
    {
      "timestamp": 45.0,
      "vehicle_count": 0,
      "vehicles": []
    },
    {
      "timestamp": 46.0,
      "vehicle_count": 0,
      "vehicles": []
    },
    {
      "timestamp": 47.0,
      "vehicle_count": 0,
      "vehicles": []
    },
    {
      "timestamp": 48.0,
      "vehicle_count": 0,
      "vehicles": []
    },
    {
      "timestamp": 49.0,
      "vehicle_count": 0,
      "vehicles": []
    },
    {
      "timestamp": 50.0,
      "vehicle_count": 0,
      "vehicles": []
    },
    {
      "timestamp": 51.0,
      "vehicle_count": 0,
      "vehicles": []
    },
    {
      "timestamp": 52.0,
      "vehicle_count": 0,
      "vehicles": []
    },
    {
      "timestamp": 53.0,
      "vehicle_count": 0,
      "vehicles": []
    },
    {
      "timestamp": 54.0,
      "vehicle_count": 0,
      "vehicles": []
    },
    {
      "timestamp": 55.0,
      "vehicle_count": 0,
      "vehicles": []
    },
    {
      "timestamp": 56.0,
      "vehicle_count": 0,
      "vehicles": []
    },
    {
      "timestamp": 57.0,
      "vehicle_count": 0,
      "vehicles": []
    },
    {
      "timestamp": 58.0,
      "vehicle_count": 0,
      "vehicles": []
    },
    {
      "timestamp": 59.0,
      "vehicle_count": 0,
      "vehicles": []
    },
    {
      "timestamp": 60.0,
      "vehicle_count": 0,
      "vehicles": []
    },
    {
      "timestamp": 61.0,
      "vehicle_count": 0,
      "vehicles": []
    },
    {
      "timestamp": 62.0,
      "vehicle_count": 0,
      "vehicles": []
    },
    {
      "timestamp": 63.0,
      "vehicle_count": 0,
      "vehicles": []
    },
    {
      "timestamp": 64.0,
      "vehicle_count": 0,
      "vehicles": []
    },
    {
      "timestamp": 65.0,
      "vehicle_count": 0,
      "vehicles": []
    },
    {
      "timestamp": 66.0,
      "vehicle_count": 0,
      "vehicles": []
    },
    {
      "timestamp": 67.0,
      "vehicle_count": 0,
      "vehicles": []
    },
    {
      "timestamp": 68.0,
      "vehicle_count": 0,
      "vehicles": []
    },
    {
      "timestamp": 69.0,
      "vehicle_count": 0,
      "vehicles": []
    },
    {
      "timestamp": 70.0,
      "vehicle_count": 0,
      "vehicles": []
    },
    {
      "timestamp": 71.0,
      "vehicle_count": 0,
      "vehicles": []
    },
    {
      "timestamp": 72.0,
      "vehicle_count": 0,
      "vehicles": []
    },
    {
      "timestamp": 73.0,
      "vehicle_count": 0,
      "vehicles": []
    },
    {
      "timestamp": 74.0,
      "vehicle_count": 0,
      "vehicles": []
    },
    {
      "timestamp": 75.0,
      "vehicle_count": 0,
      "vehicles": []
    },
    {
      "timestamp": 76.0,
      "vehicle_count": 0,
      "vehicles": []
    },
    {
      "timestamp": 77.0,
      "vehicle_count": 0,
      "vehicles": []
    },
    {
      "timestamp": 78.0,
      "vehicle_count": 0,
      "vehicles": []
    },
    {
      "timestamp": 79.0,
      "vehicle_count": 0,
      "vehicles": []
    },
    {
      "timestamp": 80.0,
      "vehicle_count": 0,
      "vehicles": []
    },
    {
      "timestamp": 81.0,
      "vehicle_count": 0,
      "vehicles": []
    },
    {
      "timestamp": 82.0,
      "vehicle_count": 0,
      "vehicles": []
    },
    {
      "timestamp": 83.0,
      "vehicle_count": 0,
      "vehicles": []
    },
    {
      "timestamp": 84.0,
      "vehicle_count": 0,
      "vehicles": []
    },
    {
      "timestamp": 85.0,
      "vehicle_count": 0,
      "vehicles": []
    },
    {
      "timestamp": 86.0,
      "vehicle_count": 0,
      "vehicles": []
    },
    {
      "timestamp": 87.0,
      "vehicle_count": 0,
      "vehicles": []
    },
    {
      "timestamp": 88.0,
      "vehicle_count": 0,
      "vehicles": []
    },
    {
      "timestamp": 89.0,
      "vehicle_count": 0,
      "vehicles": []
    },
    {
      "timestamp": 90.0,
      "vehicle_count": 0,
      "vehicles": []
    },
    {
      "timestamp": 91.0,
      "vehicle_count": 0,
      "vehicles": []
    },
    {
      "timestamp": 92.0,
      "vehicle_count": 0,
      "vehicles": []
    },
    {
      "timestamp": 93.0,
      "vehicle_count": 0,
      "vehicles": []
    },
    {
      "timestamp": 94.0,
      "vehicle_count": 0,
      "vehicles": []
    },
    {
      "timestamp": 95.0,
      "vehicle_count": 0,
      "vehicles": []
    },
    {
      "timestamp": 96.0,
      "vehicle_count": 0,
      "vehicles": []
    },
    {
      "timestamp": 97.0,
      "vehicle_count": 0,
      "vehicles": []
    },
    {
      "timestamp": 98.0,
      "vehicle_count": 0,
      "vehicles": []
    },
    {
      "timestamp": 99.0,
      "vehicle_count": 0,
      "vehicles": []
    },
    {
      "timestamp": 100.0,
      "vehicle_count": 0,
      "vehicles": []
    },
    {
      "timestamp": 101.0,
      "vehicle_count": 0,
      "vehicles": []
    },
    {
      "timestamp": 102.0,
      "vehicle_count": 0,
      "vehicles": []
    },
    {
      "timestamp": 103.0,
      "vehicle_count": 0,
      "vehicles": []
    },
    {
      "timestamp": 104.0,
      "vehicle_count": 0,
      "vehicles": []
    },
    {
      "timestamp": 105.0,
      "vehicle_count": 0,
      "vehicles": []
    },
    {
      "timestamp": 106.0,
      "vehicle_count": 0,
      "vehicles": []
    },
    {
      "timestamp": 107.0,
      "vehicle_count": 0,
      "vehicles": []
    },
    {
      "timestamp": 108.0,
      "vehicle_count": 0,
      "vehicles": []
    },
    {
      "timestamp": 109.0,
      "vehicle_count": 0,
      "vehicles": []
    },
    {
      "timestamp": 110.0,
      "vehicle_count": 0,
      "vehicles": []
    },
    {
      "timestamp": 111.0,
      "vehicle_count": 0,
      "vehicles": []
    },
    {
      "timestamp": 112.0,
      "vehicle_count": 0,
      "vehicles": []
    },
    {
      "timestamp": 113.0,
      "vehicle_count": 0,
      "vehicles": []
    },
    {
      "timestamp": 114.0,
      "vehicle_count": 0,
      "vehicles": []
    },
    {
      "timestamp": 115.0,
      "vehicle_count": 0,
      "vehicles": []
    },
    {
      "timestamp": 116.0,
      "vehicle_count": 0,
      "vehicles": []
    },
    {
      "timestamp": 117.0,
      "vehicle_count": 0,
      "vehicles": []
    },
    {
      "timestamp": 118.0,
      "vehicle_count": 0,
      "vehicles": []
    },
    {
      "timestamp": 119.0,
      "vehicle_count": 0,
      "vehicles": []
    },
    {
      "timestamp": 120.0,
      "vehicle_count": 0,
      "vehicles": []
    },
    {
      "timestamp": 121.0,
      "vehicle_count": 0,
      "vehicles": []
    },
    {
      "timestamp": 122.0,
      "vehicle_count": 0,
      "vehicles": []
    },
    {
      "timestamp": 123.0,
      "vehicle_count": 0,
      "vehicles": []
    },
    {
      "timestamp": 124.0,
      "vehicle_count": 0,
      "vehicles": []
    },
    {
      "timestamp": 125.0,
      "vehicle_count": 0,
      "vehicles": []
    },
    {
      "timestamp": 126.0,
      "vehicle_count": 0,
      "vehicles": []
    },
    {
      "timestamp": 127.0,
      "vehicle_count": 0,
      "vehicles": []
    },
    {
      "timestamp": 128.0,
      "vehicle_count": 0,
      "vehicles": []
    },
    {
      "timestamp": 129.0,
      "vehicle_count": 0,
      "vehicles": []
    },
    {
      "timestamp": 130.0,
      "vehicle_count": 0,
      "vehicles": []
    },
    {
      "timestamp": 131.0,
      "vehicle_count": 0,
      "vehicles": []
    },
    {
      "timestamp": 132.0,
      "vehicle_count": 0,
      "vehicles": []
    },
    {
      "timestamp": 133.0,
      "vehicle_count": 0,
      "vehicles": []
    },
    {
      "timestamp": 134.0,
      "vehicle_count": 0,
      "vehicles": []
    },
    {
      "timestamp": 135.0,
      "vehicle_count": 0,
      "vehicles": []
    },
    {
      "timestamp": 136.0,
      "vehicle_count": 0,
      "vehicles": []
    },
    {
      "timestamp": 137.0,
      "vehicle_count": 0,
      "vehicles": []
    },
    {
      "timestamp": 138.0,
      "vehicle_count": 0,
      "vehicles": []
    },
    {
      "timestamp": 139.0,
      "vehicle_count": 0,
      "vehicles": []
    },
    {
      "timestamp": 140.0,
      "vehicle_count": 0,
      "vehicles": []
    },
    {
      "timestamp": 141.0,
      "vehicle_count": 0,
      "vehicles": []
    },
    {
      "timestamp": 142.0,
      "vehicle_count": 0,
      "vehicles": []
    },
    {
      "timestamp": 143.0,
      "vehicle_count": 0,
      "vehicles": []
    },
    {
      "timestamp": 144.0,
      "vehicle_count": 0,
      "vehicles": []
    },
    {
      "timestamp": 145.0,
      "vehicle_count": 0,
      "vehicles": []
    },
    {
      "timestamp": 146.0,
      "vehicle_count": 0,
      "vehicles": []
    },
    {
      "timestamp": 147.0,
      "vehicle_count": 0,
      "vehicles": []
    },
    {
      "timestamp": 148.0,
      "vehicle_count": 0,
      "vehicles": []
    },
    {
      "timestamp": 149.0,
      "vehicle_count": 0,
      "vehicles": []
    },
    {
      "timestamp": 150.0,
      "vehicle_count": 0,
      "vehicles": []
    },
    {
      "timestamp": 151.0,
      "vehicle_count": 0,
      "vehicles": []
    },
    {
      "timestamp": 152.0,
      "vehicle_count": 0,
      "vehicles": []
    },
    {
      "timestamp": 153.0,
      "vehicle_count": 0,
      "vehicles": []
    },
    {
      "timestamp": 154.0,
      "vehicle_count": 0,
      "vehicles": []
    },
    {
      "timestamp": 155.0,
      "vehicle_count": 0,
      "vehicles": []
    },
    {
      "timestamp": 156.0,
      "vehicle_count": 0,
      "vehicles": []
    },
    {
      "timestamp": 157.0,
      "vehicle_count": 0,
      "vehicles": []
    },
    {
      "timestamp": 158.0,
      "vehicle_count": 0,
      "vehicles": []
    },
    {
      "timestamp": 159.0,
      "vehicle_count": 0,
      "vehicles": []
    },
    {
      "timestamp": 160.0,
      "vehicle_count": 0,
      "vehicles": []
    },
    {
      "timestamp": 161.0,
      "vehicle_count": 0,
      "vehicles": []
    },
    {
      "timestamp": 162.0,
      "vehicle_count": 0,
      "vehicles": []
    },
    {
      "timestamp": 163.0,
      "vehicle_count": 0,
      "vehicles": []
    },
    {
      "timestamp": 164.0,
      "vehicle_count": 0,
      "vehicles": []
    },
    {
      "timestamp": 165.0,
      "vehicle_count": 0,
      "vehicles": []
    },
    {
      "timestamp": 166.0,
      "vehicle_count": 0,
      "vehicles": []
    },
    {
      "timestamp": 167.0,
      "vehicle_count": 0,
      "vehicles": []
    },
    {
      "timestamp": 168.0,
      "vehicle_count": 0,
      "vehicles": []
    },
    {
      "timestamp": 169.0,
      "vehicle_count": 0,
      "vehicles": []
    },
    {
      "timestamp": 170.0,
      "vehicle_count": 0,
      "vehicles": []
    },
    {
      "timestamp": 171.0,
      "vehicle_count": 0,
      "vehicles": []
    },
    {
      "timestamp": 172.0,
      "vehicle_count": 0,
      "vehicles": []
    },
    {
      "timestamp": 173.0,
      "vehicle_count": 0,
      "vehicles": []
    },
    {
      "timestamp": 174.0,
      "vehicle_count": 0,
      "vehicles": []
    },
    {
      "timestamp": 175.0,
      "vehicle_count": 0,
      "vehicles": []
    },
    {
      "timestamp": 176.0,
      "vehicle_count": 0,
      "vehicles": []
    },
    {
      "timestamp": 177.0,
      "vehicle_count": 0,
      "vehicles": []
    },
    {
      "timestamp": 178.0,
      "vehicle_count": 0,
      "vehicles": []
    },
    {
      "timestamp": 179.0,
      "vehicle_count": 0,
      "vehicles": []
    },
    {
      "timestamp": 180.0,
      "vehicle_count": 0,
      "vehicles": []
    },
    {
      "timestamp": 181.0,
      "vehicle_count": 0,
      "vehicles": []
    },
    {
      "timestamp": 182.0,
      "vehicle_count": 0,
      "vehicles": []
    },
    {
      "timestamp": 183.0,
      "vehicle_count": 0,
      "vehicles": []
    },
    {
      "timestamp": 184.0,
      "vehicle_count": 0,
      "vehicles": []
    },
    {
      "timestamp": 185.0,
      "vehicle_count": 0,
      "vehicles": []
    },
    {
      "timestamp": 186.0,
      "vehicle_count": 0,
      "vehicles": []
    },
    {
      "timestamp": 187.0,
      "vehicle_count": 0,
      "vehicles": []
    },
    {
      "timestamp": 188.0,
      "vehicle_count": 0,
      "vehicles": []
    },
    {
      "timestamp": 189.0,
      "vehicle_count": 0,
      "vehicles": []
    },
    {
      "timestamp": 190.0,
      "vehicle_count": 0,
      "vehicles": []
    },
    {
      "timestamp": 191.0,
      "vehicle_count": 0,
      "vehicles": []
    },
    {
      "timestamp": 192.0,
      "vehicle_count": 0,
      "vehicles": []
    },
    {
      "timestamp": 193.0,
      "vehicle_count": 0,
      "vehicles": []
    },
    {
      "timestamp": 194.0,
      "vehicle_count": 0,
      "vehicles": []
    },
    {
      "timestamp": 195.0,
      "vehicle_count": 0,
      "vehicles": []
    },
    {
      "timestamp": 196.0,
      "vehicle_count": 0,
      "vehicles": []
    },
    {
      "timestamp": 197.0,
      "vehicle_count": 0,
      "vehicles": []
    },
    {
      "timestamp": 198.0,
      "vehicle_count": 0,
      "vehicles": []
    },
    {
      "timestamp": 199.0,
      "vehicle_count": 0,
      "vehicles": []
    },
    {
      "timestamp": 200.0,
      "vehicle_count": 0,
      "vehicles": []
    },
    {
      "timestamp": 201.0,
      "vehicle_count": 0,
      "vehicles": []
    },
    {
      "timestamp": 202.0,
      "vehicle_count": 0,
      "vehicles": []
    },
    {
      "timestamp": 203.0,
      "vehicle_count": 0,
      "vehicles": []
    },
    {
      "timestamp": 204.0,
      "vehicle_count": 0,
      "vehicles": []
    },
    {
      "timestamp": 205.0,
      "vehicle_count": 0,
      "vehicles": []
    },
    {
      "timestamp": 206.0,
      "vehicle_count": 0,
      "vehicles": []
    },
    {
      "timestamp": 207.0,
      "vehicle_count": 0,
      "vehicles": []
    },
    {
      "timestamp": 208.0,
      "vehicle_count": 0,
      "vehicles": []
    },
    {
      "timestamp": 209.0,
      "vehicle_count": 0,
      "vehicles": []
    },
    {
      "timestamp": 210.0,
      "vehicle_count": 0,
      "vehicles": []
    },
    {
      "timestamp": 211.0,
      "vehicle_count": 0,
      "vehicles": []
    },
    {
      "timestamp": 212.0,
      "vehicle_count": 0,
      "vehicles": []
    },
    {
      "timestamp": 213.0,
      "vehicle_count": 0,
      "vehicles": []
    },
    {
      "timestamp": 214.0,
      "vehicle_count": 0,
      "vehicles": []
    },
    {
      "timestamp": 215.0,
      "vehicle_count": 0,
      "vehicles": []
    },
    {
      "timestamp": 216.0,
      "vehicle_count": 0,
      "vehicles": []
    },
    {
      "timestamp": 217.0,
      "vehicle_count": 0,
      "vehicles": []
    },
    {
      "timestamp": 218.0,
      "vehicle_count": 0,
      "vehicles": []
    },
    {
      "timestamp": 219.0,
      "vehicle_count": 0,
      "vehicles": []
    },
    {
      "timestamp": 220.0,
      "vehicle_count": 0,
      "vehicles": []
    },
    {
      "timestamp": 221.0,
      "vehicle_count": 0,
      "vehicles": []
    },
    {
      "timestamp": 222.0,
      "vehicle_count": 0,
      "vehicles": []
    },
    {
      "timestamp": 223.0,
      "vehicle_count": 0,
      "vehicles": []
    },
    {
      "timestamp": 224.0,
      "vehicle_count": 0,
      "vehicles": []
    },
    {
      "timestamp": 225.0,
      "vehicle_count": 0,
      "vehicles": []
    },
    {
      "timestamp": 226.0,
      "vehicle_count": 0,
      "vehicles": []
    },
    {
      "timestamp": 227.0,
      "vehicle_count": 0,
      "vehicles": []
    },
    {
      "timestamp": 228.0,
      "vehicle_count": 0,
      "vehicles": []
    },
    {
      "timestamp": 229.0,
      "vehicle_count": 0,
      "vehicles": []
    },
    {
      "timestamp": 230.0,
      "vehicle_count": 0,
      "vehicles": []
    },
    {
      "timestamp": 231.0,
      "vehicle_count": 0,
      "vehicles": []
    },
    {
      "timestamp": 232.0,
      "vehicle_count": 0,
      "vehicles": []
    },
    {
      "timestamp": 233.0,
      "vehicle_count": 0,
      "vehicles": []
    },
    {
      "timestamp": 234.0,
      "vehicle_count": 0,
      "vehicles": []
    },
    {
      "timestamp": 235.0,
      "vehicle_count": 0,
      "vehicles": []
    },
    {
      "timestamp": 236.0,
      "vehicle_count": 0,
      "vehicles": []
    },
    {
      "timestamp": 237.0,
      "vehicle_count": 0,
      "vehicles": []
    },
    {
      "timestamp": 238.0,
      "vehicle_count": 0,
      "vehicles": []
    },
    {
      "timestamp": 239.0,
      "vehicle_count": 0,
      "vehicles": []
    },
    {
      "timestamp": 240.0,
      "vehicle_count": 0,
      "vehicles": []
    },
    {
      "timestamp": 241.0,
      "vehicle_count": 0,
      "vehicles": []
    },
    {
      "timestamp": 242.0,
      "vehicle_count": 0,
      "vehicles": []
    },
    {
      "timestamp": 243.0,
      "vehicle_count": 0,
      "vehicles": []
    },
    {
      "timestamp": 244.0,
      "vehicle_count": 0,
      "vehicles": []
    },
    {
      "timestamp": 245.0,
      "vehicle_count": 0,
      "vehicles": []
    },
    {
      "timestamp": 246.0,
      "vehicle_count": 0,
      "vehicles": []
    },
    {
      "timestamp": 247.0,
      "vehicle_count": 0,
      "vehicles": []
    },
    {
      "timestamp": 248.0,
      "vehicle_count": 0,
      "vehicles": []
    },
    {
      "timestamp": 249.0,
      "vehicle_count": 0,
      "vehicles": []
    },
    {
      "timestamp": 250.0,
      "vehicle_count": 0,
      "vehicles": []
    },
    {
      "timestamp": 251.0,
      "vehicle_count": 0,
      "vehicles": []
    },
    {
      "timestamp": 252.0,
      "vehicle_count": 0,
      "vehicles": []
    },
    {
      "timestamp": 253.0,
      "vehicle_count": 0,
      "vehicles": []
    },
    {
      "timestamp": 254.0,
      "vehicle_count": 0,
      "vehicles": []
    },
    {
      "timestamp": 255.0,
      "vehicle_count": 0,
      "vehicles": []
    },
    {
      "timestamp": 256.0,
      "vehicle_count": 0,
      "vehicles": []
    },
    {
      "timestamp": 257.0,
      "vehicle_count": 0,
      "vehicles": []
    },
    {
      "timestamp": 258.0,
      "vehicle_count": 0,
      "vehicles": []
    },
    {
      "timestamp": 259.0,
      "vehicle_count": 0,
      "vehicles": []
    },
    {
      "timestamp": 260.0,
      "vehicle_count": 0,
      "vehicles": []
    },
    {
      "timestamp": 261.0,
      "vehicle_count": 0,
      "vehicles": []
    },
    {
      "timestamp": 262.0,
      "vehicle_count": 0,
      "vehicles": []
    },
    {
      "timestamp": 263.0,
      "vehicle_count": 0,
      "vehicles": []
    },
    {
      "timestamp": 264.0,
      "vehicle_count": 0,
      "vehicles": []
    },
    {
      "timestamp": 265.0,
      "vehicle_count": 0,
      "vehicles": []
    },
    {
      "timestamp": 266.0,
      "vehicle_count": 0,
      "vehicles": []
    },
    {
      "timestamp": 267.0,
      "vehicle_count": 0,
      "vehicles": []
    },
    {
      "timestamp": 268.0,
      "vehicle_count": 0,
      "vehicles": []
    },
    {
      "timestamp": 269.0,
      "vehicle_count": 0,
      "vehicles": []
    },
    {
      "timestamp": 270.0,
      "vehicle_count": 0,
      "vehicles": []
    },
    {
      "timestamp": 271.0,
      "vehicle_count": 0,
      "vehicles": []
    },
    {
      "timestamp": 272.0,
      "vehicle_count": 0,
      "vehicles": []
    },
    {
      "timestamp": 273.0,
      "vehicle_count": 0,
      "vehicles": []
    },
    {
      "timestamp": 274.0,
      "vehicle_count": 0,
      "vehicles": []
    },
    {
      "timestamp": 275.0,
      "vehicle_count": 0,
      "vehicles": []
    },
    {
      "timestamp": 276.0,
      "vehicle_count": 0,
      "vehicles": []
    },
    {
      "timestamp": 277.0,
      "vehicle_count": 0,
      "vehicles": []
    },
    {
      "timestamp": 278.0,
      "vehicle_count": 0,
      "vehicles": []
    },
    {
      "timestamp": 279.0,
      "vehicle_count": 0,
      "vehicles": []
    },
    {
      "timestamp": 280.0,
      "vehicle_count": 0,
      "vehicles": []
    },
    {
      "timestamp": 281.0,
      "vehicle_count": 0,
      "vehicles": []
    },
    {
      "timestamp": 282.0,
      "vehicle_count": 0,
      "vehicles": []
    },
    {
      "timestamp": 283.0,
      "vehicle_count": 0,
      "vehicles": []
    },
    {
      "timestamp": 284.0,
      "vehicle_count": 0,
      "vehicles": []
    },
    {
      "timestamp": 285.0,
      "vehicle_count": 0,
      "vehicles": []
    },
    {
      "timestamp": 286.0,
      "vehicle_count": 0,
      "vehicles": []
    },
    {
      "timestamp": 287.0,
      "vehicle_count": 0,
      "vehicles": []
    },
    {
      "timestamp": 288.0,
      "vehicle_count": 0,
      "vehicles": []
    },
    {
      "timestamp": 289.0,
      "vehicle_count": 0,
      "vehicles": []
    },
    {
      "timestamp": 290.0,
      "vehicle_count": 0,
      "vehicles": []
    },
    {
      "timestamp": 291.0,
      "vehicle_count": 0,
      "vehicles": []
    },
    {
      "timestamp": 292.0,
      "vehicle_count": 0,
      "vehicles": []
    },
    {
      "timestamp": 293.0,
      "vehicle_count": 0,
      "vehicles": []
    },
    {
      "timestamp": 294.0,
      "vehicle_count": 0,
      "vehicles": []
    },
    {
      "timestamp": 295.0,
      "vehicle_count": 0,
      "vehicles": []
    },
    {
      "timestamp": 296.0,
      "vehicle_count": 0,
      "vehicles": []
    },
    {
      "timestamp": 297.0,
      "vehicle_count": 0,
      "vehicles": []
    },
    {
      "timestamp": 298.0,
      "vehicle_count": 0,
      "vehicles": []
    },
    {
      "timestamp": 299.0,
      "vehicle_count": 0,
      "vehicles": []
    },
    {
      "timestamp": 300.0,
      "vehicle_count": 0,
      "vehicles": []
    }
  ]
}